odoo10_addon_attribute_set-10.0.1.0.2.99.dev5-py3.8-nspkg.pth
odoo/addons/attribute_set/README.rst
odoo/addons/attribute_set/__init__.py
odoo/addons/attribute_set/__manifest__.py
odoo/addons/attribute_set/models/__init__.py
odoo/addons/attribute_set/models/attribute_attribute.py
odoo/addons/attribute_set/models/attribute_group.py
odoo/addons/attribute_set/models/attribute_option.py
odoo/addons/attribute_set/models/attribute_set.py
odoo/addons/attribute_set/models/attribute_set_owner.py
odoo/addons/attribute_set/readme/CONTRIBUTORS.rst
odoo/addons/attribute_set/readme/DESCRIPTION.rst
odoo/addons/attribute_set/readme/ROADMAP.rst
odoo/addons/attribute_set/readme/USAGE.rst
odoo/addons/attribute_set/security/attribute_security.xml
odoo/addons/attribute_set/security/ir.model.access.csv
odoo/addons/attribute_set/static/description/icon.png
odoo/addons/attribute_set/static/description/index.html
odoo/addons/attribute_set/tests/__init__.py
odoo/addons/attribute_set/tests/models.py
odoo/addons/attribute_set/tests/test_build_view.py
odoo/addons/attribute_set/tests/test_custom_attribute.py
odoo/addons/attribute_set/views/attribute_attribute_view.xml
odoo/addons/attribute_set/views/attribute_group_view.xml
odoo/addons/attribute_set/views/attribute_option_view.xml
odoo/addons/attribute_set/views/attribute_set_view.xml
odoo/addons/attribute_set/views/menu_view.xml
odoo/addons/attribute_set/wizard/__init__.py
odoo/addons/attribute_set/wizard/attribute_option_wizard.py
odoo/addons/attribute_set/wizard/attribute_option_wizard_view.xml
odoo10_addon_attribute_set-10.0.1.0.2.99.dev5.dist-info/METADATA
odoo10_addon_attribute_set-10.0.1.0.2.99.dev5.dist-info/WHEEL
odoo10_addon_attribute_set-10.0.1.0.2.99.dev5.dist-info/namespace_packages.txt
odoo10_addon_attribute_set-10.0.1.0.2.99.dev5.dist-info/top_level.txt
odoo10_addon_attribute_set-10.0.1.0.2.99.dev5.dist-info/RECORD
